webscraperr/__init__.py
webscraperr/config.py
webscraperr/db.py
webscraperr/driver.py
webscraperr/exceptions.py
webscraperr/utils.py
webscraperr-0.1.8.dist-info/METADATA
webscraperr-0.1.8.dist-info/WHEEL
webscraperr-0.1.8.dist-info/licenses/LICENSE
webscraperr-0.1.8.dist-info/RECORD
