Metadata-Version: 2.3
Name: webscraperr
Version: 0.1.8
Summary: A package for web scraping
Project-URL: Homepage, https://github.com/zvz23/webscraperr
Author-email: Ziegfred Zorrilla <ziegfredzorrilla23@gmail.com>
License-File: LICENSE
Classifier: License :: OSI Approved :: MIT License
Classifier: Operating System :: OS Independent
Classifier: Programming Language :: Python :: 3
Requires-Python: >=3.11.2
Requires-Dist: mysql-connector-python
Requires-Dist: parsel
Requires-Dist: requests
Requires-Dist: selenium-wire
Requires-Dist: undetected-chromedriver
